{
  "nodes": [
    {
      "id": "6afd652c-0239-42ea-97e2-433f2e26078b",
      "type": "code",
      "title": "1",
      "position": {
        "x": 782.0768148055382,
        "y": 422.64652900414137
      },
      "size": {
        "width": 300.0,
        "height": 200.0
      },
      "created": "2025-12-20T19:06:26.168926581+00:00",
      "modified": "2025-12-20T19:06:26.168936708+00:00",
      "tags": [],
      "contentRef": null,
      "pinned": null,
      "parent_ids": [
        "8da8f469-d549-4cad-bae2-1cf19756722d"
      ],
      "collapsed": null,
      "color": null
    },
    {
      "id": "6e89ff96-d3f9-438b-92cc-c440f0c94771",
      "type": "quiz",
      "title": "8",
      "position": {
        "x": 1194.4456157662685,
        "y": 319.68622068767996
      },
      "size": {
        "width": 300.0,
        "height": 200.0
      },
      "created": "2025-12-20T19:06:26.168984200+00:00",
      "modified": "2025-12-20T19:06:26.168987552+00:00",
      "tags": [],
      "contentRef": null,
      "pinned": null,
      "parent_ids": [],
      "collapsed": null,
      "color": null
    },
    {
      "id": "802463eb-cee6-4a90-b10f-980c9822df8f",
      "type": "code",
      "title": "2",
      "position": {
        "x": 749.5267300017439,
        "y": 648.0690834353044
      },
      "size": {
        "width": 300.0,
        "height": 200.0
      },
      "created": "2025-12-20T19:06:26.169039305+00:00",
      "modified": "2025-12-20T19:06:26.169042657+00:00",
      "tags": [],
      "contentRef": null,
      "pinned": null,
      "parent_ids": [
        "8da8f469-d549-4cad-bae2-1cf19756722d"
      ],
      "collapsed": null,
      "color": null
    },
    {
      "id": "bdfdf8ef-d538-4280-9c6c-fe24a6bcf8ac",
      "type": "code",
      "title": "6",
      "position": {
        "x": 1182.385668107628,
        "y": 437.84195533616565
      },
      "size": {
        "width": 300.0,
        "height": 200.0
      },
      "created": "2025-12-20T19:06:26.169087355+00:00",
      "modified": "2025-12-20T19:06:26.169090708+00:00",
      "tags": [],
      "contentRef": null,
      "pinned": null,
      "parent_ids": [],
      "collapsed": null,
      "color": null
    },
    {
      "id": "09c4946a-89f5-434f-9d75-4fa77407350a",
      "type": "video",
      "title": "4",
      "position": {
        "x": 1049.9298209702872,
        "y": 737.1668347963547
      },
      "size": {
        "width": 300.0,
        "height": 200.0
      },
      "created": "2025-12-20T19:06:26.169132333+00:00",
      "modified": "2025-12-20T19:06:26.169135197+00:00",
      "tags": [],
      "contentRef": null,
      "pinned": true,
      "parent_ids": [],
      "collapsed": null,
      "color": null
    },
    {
      "id": "76b06011-e235-45e3-b938-d1aafbeb5dbf",
      "type": "text",
      "title": "5",
      "position": {
        "x": 1122.4344375881626,
        "y": 614.7420013237736
      },
      "size": {
        "width": 300.0,
        "height": 200.0
      },
      "created": "2025-12-20T19:06:26.169184155+00:00",
      "modified": "2025-12-20T19:06:26.169187577+00:00",
      "tags": [],
      "contentRef": null,
      "pinned": null,
      "parent_ids": [],
      "collapsed": null,
      "color": null
    }
  ]
}